{
  "bodyColor": "White",
  "bodySprite": "Male",
  "channelSettings": [
    {
      "channelName": "!global"
    },
    {
      "channelName": "!trade"
    }
  ],
  "direction": "Down",
  "effects": [],
  "gender": "Male",
  "gold": 91290,
  "guildName": "meepers",
  "hairColor": "Default",
  "hairStyle": 5,
  "ignoreList": [],
  "isAdmin": true,
  "isDead": true,
  "mapInstanceId": "bfm",
  "name": "mink",
  "nation": "Exile",
  "statSheet": {
    "advClass": "None",
    "baseClass": "Diacht",
    "maxWeight": 42,
    "toNextLevel": 400,
    "totalExp": 2300,
    "unspentPoints": 4,
    "currentMp": 110,
    "level": 3,
    "ac": 99,
    "maximumHp": 122,
    "maximumMp": 60,
    "con": 1,
    "dex": 1,
    "int": 1,
    "str": 1,
    "wis": 1
  },
  "titles": [
    ""
  ],
  "userOptions": {
    "exchange": false,
    "fastMove": false,
    "group": true,
    "guildChat": true,
    "magic": true,
    "shout": true,
    "whisper": true,
    "wisdom": true
  },
  "x": 127,
  "y": 127
}