[
    {
        "monsterTemplateKey": "Mantis1-1",
        "lootTableKey": "blank",
        "intervalSecs": 180,
        "intervalVariancePct": 30,
        "maxAmount": 25,
        "maxPerSpawn": 15,
        "aggroRange": 6,
        "minGoldDrop": 0,
        "maxGoldDrop": 0,
        "expReward": 1620,
        "extraScriptKeys": []
    },

    {
        "monsterTemplateKey": "Mantis1-2",
        "lootTableKey": "blank",
        "intervalSecs": 180,
        "intervalVariancePct": 30,
        "maxAmount": 25,
        "maxPerSpawn": 15,
        "aggroRange": 6,
        "minGoldDrop": 0,
        "maxGoldDrop": 0,
        "expReward": 2300,
        "extraScriptKeys": []
    },

    {
        "monsterTemplateKey": "Mantis_boss1-1",
        "lootTableKey": "blank",
        "intervalSecs": 10,
        "intervalVariancePct": 30,
        "maxAmount": 1,
        "maxPerSpawn": 1,
        "aggroRange": 8,
        "minGoldDrop": 2000,
        "maxGoldDrop": 3000,
        "expReward": 13500,
        "extraScriptKeys": []
    }


]